pylidator/__init__.py
pylidator/constants.py
pylidator/error_ledger.py
pylidator/exceptions.py
pylidator/messages.py
pylidator/pylidator.py
pylidator/rules.py
pylidator/utils.py
pylidator/tests/__init__.py
pylidator/tests/pylidator_test.py
pylidator/tests/test_field_formatting.py
pylidator-1.1.6.dist-info/LICENSE
pylidator-1.1.6.dist-info/METADATA
pylidator-1.1.6.dist-info/WHEEL
pylidator-1.1.6.dist-info/top_level.txt
pylidator-1.1.6.dist-info/RECORD
