Metadata-Version: 2.1
Name: pylidator
Version: 1.1.6
Summary: A practical system for organizing validation rules.
Home-page: https://github.com/mathandpencil/pylidator
Author: Scott Stafford
Author-email: scott.stafford+pylidator@gmail.com
License: MIT
Keywords: validation validate
Classifier: Development Status :: 4 - Beta
Classifier: Intended Audience :: Developers
Classifier: License :: OSI Approved :: MIT License
Classifier: Programming Language :: Python :: 3
Classifier: Programming Language :: Python :: 3.7
Classifier: Programming Language :: Python :: 3.8
Classifier: Programming Language :: Python :: 3.9
License-File: LICENSE
Requires-Dist: future
Provides-Extra: dev
Requires-Dist: check-manifest ; extra == 'dev'
Provides-Extra: test
Requires-Dist: coverage ; extra == 'test'
